dingdingcall.py
dingdingcall-1.3.dist-info/METADATA
dingdingcall-1.3.dist-info/WHEEL
dingdingcall-1.3.dist-info/top_level.txt
dingdingcall-1.3.dist-info/RECORD
