Metadata-Version: 2.1
Name: dingdingcall
Version: 1.3
Summary: UNKNOWN
Home-page: UNKNOWN
Author: liuzihao
Author-email: UNKNOWN
License: UNKNOWN
Platform: UNKNOWN
Requires-Dist: requests
